os_testr/__init__.py
os_testr/generate_subunit.py
os_testr/subunit2html.py
os_testr/subunit_trace.py
os_testr/tests/__init__.py
os_testr/tests/base.py
os_testr/tests/test_subunit2html.py
os_testr/tests/test_subunit_trace.py
os_testr/tests/files/__init__.py
os_testr/tests/files/failing-tests
os_testr/tests/files/passing-tests
os_testr/tests/files/setup.cfg
os_testr/tests/files/stestr-conf
os_testr/tests/sample_streams/all_skips.subunit
os_testr/tests/sample_streams/successful.subunit
os_testr/tests/utils/__init__.py
os_testr/tests/utils/test_colorizer.py
os_testr/utils/__init__.py
os_testr/utils/colorizer.py
os_testr-3.0.0.dist-info/AUTHORS
os_testr-3.0.0.dist-info/LICENSE
os_testr-3.0.0.dist-info/METADATA
os_testr-3.0.0.dist-info/WHEEL
os_testr-3.0.0.dist-info/entry_points.txt
os_testr-3.0.0.dist-info/pbr.json
os_testr-3.0.0.dist-info/top_level.txt
os_testr-3.0.0.dist-info/RECORD
