Metadata-Version: 2.1
Name: os-testr
Version: 3.0.0
Summary: A testr wrapper to provide functionality for OpenStack projects
Home-page: https://docs.openstack.org/os-testr/latest/
Author: OpenStack
Author-email: openstack-discuss@lists.openstack.org
License: UNKNOWN
Platform: UNKNOWN
Classifier: Environment :: OpenStack
Classifier: Intended Audience :: Information Technology
Classifier: Intended Audience :: System Administrators
Classifier: License :: OSI Approved :: Apache Software License
Classifier: Operating System :: POSIX :: Linux
Classifier: Programming Language :: Python
Classifier: Programming Language :: Python :: 3
Classifier: Programming Language :: Python :: 3.8
Classifier: Programming Language :: Python :: 3.9
Classifier: Programming Language :: Python :: 3 :: Only
Classifier: Programming Language :: Python :: Implementation :: CPython
Requires-Python: >=3.8
Requires-Dist: pbr (!=2.1.0,>=2.0.0)
Requires-Dist: python-subunit (>=1.0.0)
Requires-Dist: testtools (>=2.2.0)
